abstract_database/__init__.py
abstract_database/all_imps.py
abstract_database/dbManager.py
abstract_database/get_all_imports.py
abstract_database/imports.py
abstract_database/connect/__init__.py
abstract_database/connect/conn_mgr_connect.py
abstract_database/connect/imports.py
abstract_database/fetch_utils/__init__.py
abstract_database/fetch_utils/imports.py
abstract_database/fetch_utils/fetch_utils/__init__.py
abstract_database/fetch_utils/fetch_utils/insert_utils.py
abstract_database/fetch_utils/fetch_utils/query_utils.py
abstract_database/fetch_utils/fetch_utils/remove_utils.py
abstract_database/fetch_utils/fetch_utils/select_utils.py
abstract_database/fetch_utils/fetch_utils/update_utils.py
abstract_database/fetch_utils/utils/__init__.py
abstract_database/fetch_utils/utils/build_utils.py
abstract_database/fetch_utils/utils/result_utils.py
abstract_database/fetch_utils/utils/toggle_utils.py
abstract_database/imports/__init__.py
abstract_database/imports/managers/__init__.py
abstract_database/imports/managers/columnNamesManager.py
abstract_database/imports/managers/connectionManager.py
abstract_database/imports/managers/imports.py
abstract_database/imports/managers/tableManager.py
abstract_database/imports/src/__init__.py
abstract_database/imports/src/paths.py
abstract_database/imports/src/envs/__init__.py
abstract_database/imports/src/envs/imports.py
abstract_database/imports/src/envs/py/__init__.py
abstract_database/imports/src/envs/py/imports.py
abstract_database/imports/src/envs/py/postgres.py
abstract_database/imports/src/envs/py/queues.py
abstract_database/imports/src/envs/py/rabbit.py
abstract_database/imports/src/envs/py/solana.py
abstract_database/imports/src/init_imports/__init__.py
abstract_database/imports/src/init_imports/abstract_imports.py
abstract_database/imports/src/init_imports/db_imports.py
abstract_database/imports/src/init_imports/init_imports.py
abstract_database/imports/src/utils/__init__.py
abstract_database/imports/src/utils/build.py
abstract_database-0.0.2.120.dist-info/METADATA
abstract_database-0.0.2.120.dist-info/WHEEL
abstract_database-0.0.2.120.dist-info/top_level.txt
abstract_database-0.0.2.120.dist-info/RECORD
