Metadata-Version: 2.4
Name: abstract_database
Version: 0.0.2.120
Summary: A lightweight' , 'env-driven toolkit for Postgres connections' , 'table helpers' , 'and Pandas exports.
Home-page: https://github.com/AbstractEndeavors/abstract_database
Author: putkoff
Author-email: partners@abstractendeavors.com
Classifier: Development Status :: 3 - Alpha
Classifier: Intended Audience :: Developers
Classifier: License :: OSI Approved :: MIT License
Classifier: Programming Language :: Python :: 3
Classifier: Programming Language :: Python :: 3.11
Requires-Python: >=3.6
Requires-Dist: pillow
Requires-Dist: abstract_apis
Requires-Dist: abstract_database
Requires-Dist: abstract_gui
Requires-Dist: abstract_math
Requires-Dist: abstract_pandas
Requires-Dist: abstract_security
Requires-Dist: abstract_utilities
Requires-Dist: numpy
Requires-Dist: pandas
Requires-Dist: psycopg2
Requires-Dist: sqlalchemy
Requires-Dist: abstract_pandas
Dynamic: author
Dynamic: author-email
Dynamic: classifier
Dynamic: description
Dynamic: description-content-type
Dynamic: home-page
Dynamic: requires-dist
Dynamic: requires-python
Dynamic: summary
